Workbook

Sheet Instructions
B1: DARES IMG Financial Proposal Template — Form 6
B2: REA / DARES PMU — Bidder-Facing Financial Proposal Workbook
B5: COLOUR CODING
B6: Blue text | C6: Hardcoded input cells — bidder enters data here
B7: Black text | C7: Calculated formula cells — do not overwrite
B8: Green text | C8: Cross-sheet links — values pulled automatically from other tabs
B9: Yellow background | C9: Input cells requiring bidder data
B10: Green background | C10: Auto-calculated or linked values
B12: SUBMISSION RULES
B13: Currency | C13: Use USD throughout unless Bid Data Sheet specifies NGN. State exchange rate used on Tab 1 — Bid Summary.
B14: Grant ceiling | C14: Requested grant % (Tab 3) must not exceed the ceiling stated in the Bid Data Sheet. An automatic check is built in.
B15: All tabs required | C15: All 11 tabs must be completed and submitted. Incomplete workbooks may be deemed non-responsive.
B16: PDF summary | C16: Print Tab 1 (Bid Summary) to PDF and sign. Submit both the signed PDF and this Excel workbook.
B17: Assumptions | C17: State all key assumptions in the Comments column on each tab. Undisclosed assumptions may not be used to justify post-award price changes.
B18: Milestone % | C18: Milestone tranche percentages on Tab 11 must match the grant agreement tranche schedule confirmed in the Bid Data Sheet.
B20: TABS IN THIS WORKBOOK
B21: Tab 1 — Bid Summary | C21: Executive summary: key metrics auto-linked from other tabs. Sign and submit as PDF.
B22: Tab 2 — Eligible CAPEX | C22: Itemised eligible CAPEX by category. Forms the basis for grant calculation.
B23: Tab 3 — Ineligible CAPEX | C23: Items not eligible for grant — must be disclosed for transparency.
B24: Tab 4 — Grant Request | C24: Auto-calculates grant ask from Tab 2; checks against ceiling.
B25: Tab 5 — Capital Stack | C25: Equity, debt, and grant funding structure.
B26: Tab 6 — Tariffs and Settlement | C26: Customer tariffs by class, grid energy purchase rate, and DUOS assumptions.
B27: Tab 7 — Revenue Forecast | C27: 10-year revenue projection by customer class with collection rate.
B28: Tab 8 — OPEX | C28: Annual operating costs for the project.
B29: Tab 9 — Cash Flow and DSCR | C29: Project cash flow, debt service, and debt service coverage ratio.
B30: Tab 10 — Sensitivities | C30: 7-scenario sensitivity table for key risk variables.
B31: Tab 11 — Milestone Schedule | C31: Grant tranche schedule aligned to verification milestones.

Sheet 1 - Bid Summary
B1: DARES IMG FINANCIAL PROPOSAL — BID SUMMARY (Form 6, Tab 1)
B2: Sign this tab as PDF and submit with the Excel workbook
A4: BIDDER INFORMATION
B5: Bidder / Consortium Lead | D5: Legal name of entity submitting this bid
B6: Lot name / number | D6: As stated in Bid Data Sheet
B7: Exchange rate used (USD:NGN) | D7: Source and date — e.g. CBN I&E Window, 15 Jun 2026
B8: Submission date | D8: DD-MMM-YYYY
A10: PROJECT FINANCIALS
B11: Total eligible CAPEX (USD) | C11: ='2 - Eligible CAPEX'!C22 -> 0
B12: Total ineligible CAPEX (USD) | C12: ='3 - Ineligible CAPEX'!C12 -> 0
B13: Total project CAPEX (USD) | C13: =C9+C10 -> 0
B14: Requested grant % of eligible CAPEX | C14: ='4 - Grant Request'!C5 -> 0 | D14: 0.0%
B15: Requested grant amount (USD) | C15: ='4 - Grant Request'!C6 -> 0
B16: Equity contribution (USD) | C16: ='5 - Capital Stack'!C5 -> 0
B17: Debt amount (USD) | C17: ='5 - Capital Stack'!C6 -> 0
B18: Total funding (Grant + Equity + Debt) (USD) | C18: ='5 - Capital Stack'!C9 -> 0
B19: Funding gap (Total CAPEX less Total Funding) | C19: =C11-C15 -> 0
A21: TARIFF AND COMMERCIAL
B22: Residential tariff (USD/kWh) | C22: ='6 - Tariffs Settlement'!C5 -> 0
B23: Commercial tariff (USD/kWh) | C23: ='6 - Tariffs Settlement'!C6 -> 0
B24: PUE/MSME tariff (USD/kWh) | C24: ='6 - Tariffs Settlement'!C7 -> 0
B25: Grid energy purchase tariff payable to DisCo (USD/kWh) | C25: ='6 - Tariffs Settlement'!C8 -> 0
B26: DUOS/network-use charge (USD/kWh) | C26: ='6 - Tariffs Settlement'!C9 -> 0
A28: KEY MILESTONES
B29: Expected financial close date | D29: DD-MMM-YYYY
B30: Expected commissioning date | D30: DD-MMM-YYYY
B31: Expected full connections date | D31: DD-MMM-YYYY
B32: One-year utilisation verification date | D32: DD-MMM-YYYY
A34: GRANT EFFICIENCY CHECK
B35: Grant as % of total project CAPEX | C35: =IF(C11>0,C12/C11,0) -> 0 | D35: 0.0%
B36: Grant per committed connection (USD)
B37: Within grant ceiling? | C37: ='4 - Grant Request'!C8 -> 0 | D37: @

Sheet 2 - Eligible CAPEX
B1: Tab 2 — Eligible CAPEX (Basis for Grant Calculation)
B2: Enter amounts in USD. Blue cells are bidder inputs. Evidence column shows what must be provided to IVA post-award.
B3: CAPEX Category | C3: Eligible? | D3: Bidder Amount (USD) | E3: Notes / Assumptions | F3: Evidence Required (Post-Award)
B4: Solar PV modules, mounting structures, DC cabling and BOS | C4: Yes | D4: 0 | E4: State supplier, model, quantity, unit cost assumption | F4: Supplier invoice, delivery note, serial number list, installation certificate, geotagged photos
B5: BESS — cells, modules, and BMS | C5: Yes | D5: 0 | E5: State supplier, model, quantity, unit cost assumption | F5: Supplier invoice, OEM certificate, commissioning test report
B6: PCS / Inverters and energy management system | C6: Yes | D6: 0 | E6: State supplier, model, quantity, unit cost assumption | F6: Supplier invoice, OEM certificate, commissioning test
B7: Backup generator (if permitted by Bid Data Sheet) | C7: Conditional — confirm with REA | D7: 0 | E7: State supplier, model, quantity, unit cost assumption | F7: Invoice, emissions specification, commissioning test, capacity justification
B8: Distribution network rehabilitation — conductors, poles, transformers | C8: Yes — within approved service area | D8: 0 | E8: State supplier, model, quantity, unit cost assumption | F8: BoQ, work completion certificate, as-built drawings, independent inspection, geotagged photos
B9: Distribution network extension — new service connections | C9: Yes — within approved service area | D9: 0 | E9: State supplier, model, quantity, unit cost assumption | F9: BoQ, completion certificate, as-built drawings, geotagged photos
B10: Interconnection equipment and protection systems at POI | C10: Yes — required for DisCo interface | D10: 0 | E10: State supplier, model, quantity, unit cost assumption | F10: POI inspection record, protection relay settings, NEMSA/DisCo confirmation, invoices
B11: Customer prepaid/smart meters — supply and installation | C11: Yes — when installed and verified | D11: 0 | E11: State supplier, model, quantity, unit cost assumption | F11: Meter serial number list, calibration certificate, customer register, activation data
B12: Bulk meter(s) for grid energy measurement | C12: Yes — required for settlement | D12: 0 | E12: State supplier, model, quantity, unit cost assumption | F12: DisCo/NEMSA confirmation, calibration certificate, meter data protocol
B13: SCADA and remote monitoring system (directly required for IMG operation) | C13: Yes | D13: 0 | E13: State supplier, model, quantity, unit cost assumption | F13: System acceptance test, data connectivity confirmation, operator manual
B14: Civil works directly tied to approved assets (foundations, earthing, cabling trenches) | C14: Yes — where verified | D14: 0 | E14: State supplier, model, quantity, unit cost assumption | F14: Engineer completion certificate, inspection report, invoices
B15: Spare parts and consumables (first-year critical spares only where approved) | C15: Conditional — confirm with REA | D15: 0 | E15: State supplier, model, quantity, unit cost assumption | F15: Approved spare parts list, invoices, delivery confirmation
B16: TOTAL ELIGIBLE CAPEX | D16: =SUM(D4:D15) -> 0 | E16: Auto-calculated. This figure feeds the Grant Request tab.

Sheet 3 - Ineligible CAPEX
B1: Tab 3 — Ineligible CAPEX (Transparency Disclosure)
B2: These items are NOT eligible for grant funding. Disclose for transparency and for evaluators to assess full project cost.
B3: Ineligible CAPEX Category | C3: Amount (USD) | D3: Notes
B4: Land acquisition and site preparation costs | C4: 0 | D4: Describe if applicable
B5: Developer profit and performance fees | C5: 0 | D5: Describe if applicable
B6: General corporate overhead and head-office allocation | C6: 0 | D6: Describe if applicable
B7: Taxes and import duties (unless expressly permitted in Bid Data Sheet) | C7: 0 | D7: Describe if applicable
B8: Feasibility studies, bid preparation, and due diligence costs | C8: 0 | D8: Describe if applicable
B9: Financing costs — arrangement fees, commitment fees, interest during construction | C9: 0 | D9: Describe if applicable
B10: Working capital and initial O&M reserve | C10: 0 | D10: Describe if applicable
B11: Penalties, liquidated damages, and insurance claims | C11: 0 | D11: Describe if applicable
B12: Other items not on the eligible CAPEX list — specify below | C12: 0 | D12: Describe if applicable
B13: Other (specify) | C13: 0 | D13: Describe if applicable
B14: TOTAL INELIGIBLE CAPEX | C14: =SUM(C4:C13) -> 0

Sheet 4 - Grant Request
B1: Tab 4 — Grant Request
B2: Grant = Eligible CAPEX × Requested %. Must not exceed ceiling. Auto-check built in.
B4: Total eligible CAPEX (from Tab 2) | C4: ='2 - Eligible CAPEX'!C22 -> 0 | D4: Auto-linked — do not edit
B5: Grant ceiling % (from Bid Data Sheet — insert before issue) | D5: REA/DARES to complete before issuing this workbook
A7: BIDDER GRANT REQUEST
B8: Requested grant % of eligible CAPEX | D8: Must be ≤ ceiling in row 3
B9: Requested grant amount (USD) | C9: =C4*C6 -> 0 | D9: Auto-calculated: Eligible CAPEX × Grant %
A11: GRANT CEILING CHECK
B12: Grant ceiling % | D12: Copy from row 3
B13: Maximum permissible grant amount (USD) | C13: =C4*C9 -> 0 | D13: Auto-calculated ceiling
B14: Bidder grant within ceiling? | C14: =IF(C6<=C9,"YES — within ceiling","NO — EXCEEDS CEILING — REVISE") -> YES — within ceiling | D14: Auto-check
A16: GRANT CALCULATION CHECK
B17: Total project CAPEX (Eligible + Ineligible) | C17: ='2 - Eligible CAPEX'!C22+'3 - Ineligible CAPEX'!C12 -> 0 | D17: Total project cost — evaluators use this to assess grant efficiency
B18: Grant as % of total project CAPEX | C18: =IF(C17>0,C6/C17,0) -> 0 | D18: Grants that represent >60% of total CAPEX may raise VFM questions
B19: Eligible CAPEX as % of total CAPEX | C19: =IF(C17>0,C4/C17,0) -> 0 | D19: Proportion of project cost that is grant-eligible

Sheet 5 - Capital Stack
B1: Tab 5 — Capital Stack
B2: Show all sources of funding. Total must equal or exceed total project CAPEX.
B3: Funding Source | C3: Amount (USD) | D3: Terms / Notes
B4: Grant (auto-linked from Tab 4) | C4: ='4 - Grant Request'!C6 -> 0 | D4: Auto-linked from Grant Request tab
B5: Equity — developer own funds | D5: Name of shareholder; board resolution reference
B6: Equity — co-investor (if any) | D6: Name of co-investor; commitment letter reference
B7: Debt — senior lender | D7: Lender name; indicative rate %; tenor years; grace period months
B8: Debt — subordinated / mezzanine (if any) | D8: Lender name; terms; ranking vs senior debt
B9: Other — specify | D9: Describe source and conditionality
B11: TOTAL FUNDING (sum of all sources) | C11: =SUM(C4:C9) -> 0 | D11: Must equal or exceed total project CAPEX
B12: Total project CAPEX (from Tabs 2+3) | C12: ='2 - Eligible CAPEX'!C22+'3 - Ineligible CAPEX'!C12 -> 0 | D12: Auto-linked
B13: Funding gap (Total CAPEX less Total Funding) | C13: =C10-C11 -> 0 | D13: Must be zero or negative for bid to be fully funded

Sheet 6 - Tariffs Settlement
B1: Tab 6 — Tariffs and Settlement Assumptions
B2: All tariffs in USD/kWh unless Bid Data Sheet specifies NGN. State exchange rate on Tab 1.
B3: Item | C3: Rate / Assumption | D3: Notes
A4: CUSTOMER TARIFFS
B5: Residential tariff (USD/kWh) | D5: State assumption basis and source
B6: Commercial tariff (USD/kWh) | D6: State assumption basis and source
B7: PUE/MSME tariff (USD/kWh) | D7: State assumption basis and source
B8: Anchor customer tariff (USD/kWh or flat rate) | D8: State assumption basis and source
B9: Annual tariff escalation rate (%/year) | D9: State assumption basis and source
B10: NERC tariff regulatory pathway | D10: State assumption basis and source
A12: DISCO SETTLEMENT
B13: Grid energy purchase tariff payable to DisCo (USD/kWh) | D13: State assumption basis and source
B14: DUOS / network-use charge (USD/kWh) | D14: State assumption basis and source
B15: Monthly invoice settlement cycle (days after month end) | D15: State assumption basis and source
B16: Legacy customer arrears treatment | D16: State assumption basis and source
B17: Dispute resolution reference (per tripartite agreement) | D17: State assumption basis and source
A19: KEY COMMERCIAL ASSUMPTIONS
B20: System availability target (%/year) | D20: State assumption basis and source
B21: Minimum supply hours per day (committed) | D21: State assumption basis and source
B22: Annual demand growth assumption (%/year) | D22: State assumption basis and source
B23: Grid supply hours per day (base case assumption) | D23: State assumption basis and source
B24: Battery replacement assumed in Year | D24: State assumption basis and source
B25: Battery replacement cost assumption (USD) | D25: State assumption basis and source

Sheet 7 - Revenue Forecast
B1: Tab 7 — Revenue Forecast (10-Year)
B2: State assumptions in Notes column. Collection rate applied to gross revenue gives collected revenue.
B3: Revenue Item | C3: Year 1 | D3: Year 2 | E3: Year 3 | F3: Year 4 | G3: Year 5 | H3: Year 6 | I3: Year 7 | J3: Year 8 | K3: Year 9 | L3: Year 10 | M3: Unit | N3: Notes / Assumptions
A4: CONNECTIONS AND DEMAND
B5: Residential customers (number) | C5: 0 | D5: 0 | E5: 0 | F5: 0 | G5: 0 | H5: 0 | I5: 0 | J5: 0 | K5: 0 | L5: 0 | M5: #,##0 | N5: Ramp up from commissioning to full target
B6: Commercial customers (number) | C6: 0 | D6: 0 | E6: 0 | F6: 0 | G6: 0 | H6: 0 | I6: 0 | J6: 0 | K6: 0 | L6: 0 | M6: #,##0 | N6: Include MSMEs in commercial or split separately
B7: PUE/MSME customers (number) | C7: 0 | D7: 0 | E7: 0 | F7: 0 | G7: 0 | H7: 0 | I7: 0 | J7: 0 | K7: 0 | L7: 0 | M7: #,##0 | N7: Anchor and productive use customers
B8: Average residential consumption (kWh/customer/month) | C8: 0 | D8: 0 | E8: 0 | F8: 0 | G8: 0 | H8: 0 | I8: 0 | J8: 0 | K8: 0 | L8: 0 | M8: #,##0.0 | N8: MTF tier assumption
B9: Average commercial consumption (kWh/customer/month) | C9: 0 | D9: 0 | E9: 0 | F9: 0 | G9: 0 | H9: 0 | I9: 0 | J9: 0 | K9: 0 | L9: 0 | M9: #,##0.0 | N9: Based on customer segmentation
B10: Average PUE consumption (kWh/customer/month) | C10: 0 | D10: 0 | E10: 0 | F10: 0 | G10: 0 | H10: 0 | I10: 0 | J10: 0 | K10: 0 | L10: 0 | M10: #,##0.0 | N10: Based on PUE anchor assessment
A12: ENERGY SOLD
B13: Residential kWh sold (annual) | C13: 0 | D13: 0 | E13: 0 | F13: 0 | G13: 0 | H13: 0 | I13: 0 | J13: 0 | K13: 0 | L13: 0 | M13: #,##0 | N13: = connections × monthly kWh × 12
B14: Commercial kWh sold (annual) | C14: 0 | D14: 0 | E14: 0 | F14: 0 | G14: 0 | H14: 0 | I14: 0 | J14: 0 | K14: 0 | L14: 0 | M14: #,##0 | N14: = connections × monthly kWh × 12
B15: PUE/MSME kWh sold (annual) | C15: 0 | D15: 0 | E15: 0 | F15: 0 | G15: 0 | H15: 0 | I15: 0 | J15: 0 | K15: 0 | L15: 0 | M15: #,##0 | N15: = connections × monthly kWh × 12
B16: Total kWh sold (annual) | C16: 0 | D16: 0 | E16: 0 | F16: 0 | G16: 0 | H16: 0 | I16: 0 | J16: 0 | K16: 0 | L16: 0 | M16: #,##0 | N16: Sum of above
A18: REVENUE
B19: Residential gross revenue (USD) | C19: 0 | D19: 0 | E19: 0 | F19: 0 | G19: 0 | H19: 0 | I19: 0 | J19: 0 | K19: 0 | L19: 0 | M19: "$"#,##0;("$"#,##0);"-" | N19: = kWh × residential tariff
B20: Commercial gross revenue (USD) | C20: 0 | D20: 0 | E20: 0 | F20: 0 | G20: 0 | H20: 0 | I20: 0 | J20: 0 | K20: 0 | L20: 0 | M20: "$"#,##0;("$"#,##0);"-" | N20: = kWh × commercial tariff
B21: PUE/MSME gross revenue (USD) | C21: 0 | D21: 0 | E21: 0 | F21: 0 | G21: 0 | H21: 0 | I21: 0 | J21: 0 | K21: 0 | L21: 0 | M21: "$"#,##0;("$"#,##0);"-" | N21: = kWh × PUE tariff
B22: Total gross revenue (USD) | C22: 0 | D22: 0 | E22: 0 | F22: 0 | G22: 0 | H22: 0 | I22: 0 | J22: 0 | K22: 0 | L22: 0 | M22: "$"#,##0;("$"#,##0);"-" | N22: Sum of above
B23: Collection rate (%) | C23: 0 | D23: 0 | E23: 0 | F23: 0 | G23: 0 | H23: 0 | I23: 0 | J23: 0 | K23: 0 | L23: 0 | M23: 0.0% | N23: Realistic collection rate assumption with basis stated
B24: Total collected revenue (USD) | C24: 0 | D24: 0 | E24: 0 | F24: 0 | G24: 0 | H24: 0 | I24: 0 | J24: 0 | K24: 0 | L24: 0 | M24: "$"#,##0;("$"#,##0);"-" | N24: = gross revenue × collection rate
A26: GRID ENERGY COSTS
B27: Grid import kWh (annual) | C27: 0 | D27: 0 | E27: 0 | F27: 0 | G27: 0 | H27: 0 | I27: 0 | J27: 0 | K27: 0 | L27: 0 | M27: #,##0 | N27: Estimated grid energy purchased from DisCo
B28: Grid energy cost — DisCo payment (USD) | C28: 0 | D28: 0 | E28: 0 | F28: 0 | G28: 0 | H28: 0 | I28: 0 | J28: 0 | K28: 0 | L28: 0 | M28: "$"#,##0;("$"#,##0);"-" | N28: = grid import kWh × DisCo tariff
B29: DUOS/network-use charge (USD) | C29: 0 | D29: 0 | E29: 0 | F29: 0 | G29: 0 | H29: 0 | I29: 0 | J29: 0 | K29: 0 | L29: 0 | M29: "$"#,##0;("$"#,##0);"-" | N29: = grid import kWh × DUOS rate
B30: Net revenue after DisCo settlement (USD) | C30: 0 | D30: 0 | E30: 0 | F30: 0 | G30: 0 | H30: 0 | I30: 0 | J30: 0 | K30: 0 | L30: 0 | M30: "$"#,##0;("$"#,##0);"-" | N30: = collected revenue − grid cost − DUOS

Sheet 8 - OPEX
B1: Tab 8 — Annual Operating Costs (OPEX)
B2: Enter annual OPEX in USD. Year 1 = first full year of operation post-commissioning.
B3: OPEX Category | C3: Year 1 | D3: Year 2 | E3: Year 3 | F3: Year 4 | G3: Year 5 | H3: Year 6 | I3: Year 7 | J3: Year 8 | K3: Year 9 | L3: Year 10 | M3: Unit | N3: Notes
B4: O&M staffing — site technician(s) | C4: 0 | D4: 0 | E4: 0 | F4: 0 | G4: 0 | H4: 0 | I4: 0 | J4: 0 | K4: 0 | L4: 0 | M4: "$"#,##0;("$"#,##0);"-" | N4: Local technical staff; salary, benefits, training
B5: O&M staffing — regional/remote support | C5: 0 | D5: 0 | E5: 0 | F5: 0 | G5: 0 | H5: 0 | I5: 0 | J5: 0 | K5: 0 | L5: 0 | M5: "$"#,##0;("$"#,##0);"-" | N5: Head office or outsourced technical support allocation
B6: Routine maintenance — PV and BESS | C6: 0 | D6: 0 | E6: 0 | F6: 0 | G6: 0 | H6: 0 | I6: 0 | J6: 0 | K6: 0 | L6: 0 | M6: "$"#,##0;("$"#,##0);"-" | N6: Module cleaning, inverter checks, battery testing
B7: Routine maintenance — distribution network | C7: 0 | D7: 0 | E7: 0 | F7: 0 | G7: 0 | H7: 0 | I7: 0 | J7: 0 | K7: 0 | L7: 0 | M7: "$"#,##0;("$"#,##0);"-" | N7: Line inspection, pole maintenance, transformer servicing
B8: Spare parts and consumables | C8: 0 | D8: 0 | E8: 0 | F8: 0 | G8: 0 | H8: 0 | I8: 0 | J8: 0 | K8: 0 | L8: 0 | M8: "$"#,##0;("$"#,##0);"-" | N8: Critical spares holding and annual replacements
B9: Insurance — assets and liability | C9: 0 | D9: 0 | E9: 0 | F9: 0 | G9: 0 | H9: 0 | I9: 0 | J9: 0 | K9: 0 | L9: 0 | M9: "$"#,##0;("$"#,##0);"-" | N9: Asset insurance rate and estimated premium
B10: Land lease / community payments | C10: 0 | D10: 0 | E10: 0 | F10: 0 | G10: 0 | H10: 0 | I10: 0 | J10: 0 | K10: 0 | L10: 0 | M10: "$"#,##0;("$"#,##0);"-" | N10: Annual site lease, community development contribution if any
B11: Monitoring and data systems — annual subscription/licence | C11: 0 | D11: 0 | E11: 0 | F11: 0 | G11: 0 | H11: 0 | I11: 0 | J11: 0 | K11: 0 | L11: 0 | M11: "$"#,##0;("$"#,##0);"-" | N11: SCADA/AMI platform, data costs, cybersecurity
B12: Security | C12: 0 | D12: 0 | E12: 0 | F12: 0 | G12: 0 | H12: 0 | I12: 0 | J12: 0 | K12: 0 | L12: 0 | M12: "$"#,##0;("$"#,##0);"-" | N12: Site security — guards, fencing maintenance, alarm
B13: Customer service and billing | C13: 0 | D13: 0 | E13: 0 | F13: 0 | G13: 0 | H13: 0 | I13: 0 | J13: 0 | K13: 0 | L13: 0 | M13: "$"#,##0;("$"#,##0);"-" | N13: Metering platform, mobile money, customer support
B14: Management fee / head-office allocation (if applicable) | C14: 0 | D14: 0 | E14: 0 | F14: 0 | G14: 0 | H14: 0 | I14: 0 | J14: 0 | K14: 0 | L14: 0 | M14: "$"#,##0;("$"#,##0);"-" | N14: Developer overhead allocation; note if not eligible for grant
B15: Working capital and reserves (annual contribution) | C15: 0 | D15: 0 | E15: 0 | F15: 0 | G15: 0 | H15: 0 | I15: 0 | J15: 0 | K15: 0 | L15: 0 | M15: "$"#,##0;("$"#,##0);"-" | N15: O&M reserve, debt service reserve if structured
B16: Other — specify | C16: 0 | D16: 0 | E16: 0 | F16: 0 | G16: 0 | H16: 0 | I16: 0 | J16: 0 | K16: 0 | L16: 0 | M16: "$"#,##0;("$"#,##0);"-" | N16: Describe
B17: TOTAL ANNUAL OPEX | C17: =SUM(C4:C16) -> 0 | D17: =SUM(D4:D16) -> 0 | E17: =SUM(E4:E16) -> 0 | F17: =SUM(F4:F16) -> 0 | G17: =SUM(G4:G16) -> 0 | H17: =SUM(H4:H16) -> 0 | I17: =SUM(I4:I16) -> 0 | J17: =SUM(J4:J16) -> 0 | ... L17: =SUM(L4:L16) -> 0

Sheet 9 - Cash Flow and DSCR
B1: Tab 9 — Project Cash Flow and Debt Service Coverage Ratio (DSCR)
B2: All values in USD. DSCR = EBITDA / Annual Debt Service. Lender threshold typically ≥ 1.3x.
B3: Item | C3: Year 1 | D3: Year 2 | E3: Year 3 | F3: Year 4 | G3: Year 5 | H3: Year 6 | I3: Year 7 | J3: Year 8 | K3: Year 9 | L3: Year 10 | M3: Notes
A4: PROJECT CASH FLOW
B5: Total collected revenue (from Tab 7) | C5: ='7 - Revenue Forecast'!L21 -> 0 | D5: ='7 - Revenue Forecast'!L21 -> 0 | E5: ='7 - Revenue Forecast'!L21 -> 0 | F5: ='7 - Revenue Forecast'!L21 -> 0 | G5: ='7 - Revenue Forecast'!L21 -> 0 | H5: ='7 - Revenue Forecast'!L21 -> 0 | I5: ='7 - Revenue Forecast'!L21 -> 0 | J5: ='7 - Revenue Forecast'!L21 -> 0 | K5: ='7 - Revenue Forecast'!L21 -> 0 | L5: ='7 - Revenue Forecast'!L21 -> 0
B6: Less: Total OPEX (from Tab 8) | C6: ='8 - OPEX'!C17 -> 0 | D6: ='8 - OPEX'!C17 -> 0 | E6: ='8 - OPEX'!C17 -> 0 | F6: ='8 - OPEX'!C17 -> 0 | G6: ='8 - OPEX'!C17 -> 0 | H6: ='8 - OPEX'!C17 -> 0 | I6: ='8 - OPEX'!C17 -> 0 | J6: ='8 - OPEX'!C17 -> 0 | K6: ='8 - OPEX'!C17 -> 0 | L6: ='8 - OPEX'!C17 -> 0
B7: EBITDA (Revenue minus OPEX) | C7: =C5-C6 -> 0 | D7: =D5-C6 -> 0 | E7: =E5-C6 -> 0 | F7: =F5-C6 -> 0 | G7: =G5-C6 -> 0 | H7: =H5-C6 -> 0 | I7: =I5-C6 -> 0 | J7: =J5-C6 -> 0 | K7: =K5-C6 -> 0 | L7: =L5-C6 -> 0
B8: CAPEX (Year 0 = total; Year 1+ = 0 unless phased) | C8: 0 | D8: 0 | E8: 0 | F8: 0 | G8: 0 | H8: 0 | I8: 0 | J8: 0 | K8: 0 | L8: 0
B9: Grant receipt by milestone | C9: 0 | D9: 0 | E9: 0 | F9: 0 | G9: 0 | H9: 0 | I9: 0 | J9: 0 | K9: 0 | L9: 0
B10: Equity contribution | C10: 0 | D10: 0 | E10: 0 | F10: 0 | G10: 0 | H10: 0 | I10: 0 | J10: 0 | K10: 0 | L10: 0
B11: Debt drawdown | C11: 0 | D11: 0 | E11: 0 | F11: 0 | G11: 0 | H11: 0 | I11: 0 | J11: 0 | K11: 0 | L11: 0
A12: DEBT SERVICE
B13: Annual debt repayment (principal) | C13: 0 | D13: 0 | E13: 0 | F13: 0 | G13: 0 | H13: 0 | I13: 0 | J13: 0 | K13: 0 | L13: 0
B14: Annual interest payment | C14: 0 | D14: 0 | E14: 0 | F14: 0 | G14: 0 | H14: 0 | I14: 0 | J14: 0 | K14: 0 | L14: 0
B15: Total annual debt service | C15: =C12+C13 -> 0 | D15: =D12+D13 -> 0 | E15: =E12+E13 -> 0 | F15: =F12+F13 -> 0 | G15: =G12+G13 -> 0 | H15: =H12+H13 -> 0 | I15: =I12+I13 -> 0 | J15: =J12+J13 -> 0 | ... L15: =L12+L13 -> 0
A16: RETURNS AND COVERAGE
B17: Net cash flow after debt service | C17: =C7-C14 -> 0 | D17: =D7-D14 -> 0 | E17: =E7-E14 -> 0 | F17: =F7-F14 -> 0 | G17: =G7-G14 -> 0 | H17: =H7-H14 -> 0 | I17: =I7-I14 -> 0 | J17: =J7-J14 -> 0 | ... L17: =L7-L14 -> 0
B18: Cumulative net cash flow | C18: =C16 -> 0 | D18: =C17+D16 -> 0 | E18: =D17+E16 -> 0 | F18: =E17+F16 -> 0 | G18: =F17+G16 -> 0 | H18: =G17+H16 -> 0 | I18: =H17+I16 -> 0 | J18: =I17+J16 -> 0 | K18: =J17+K16 -> 0 | L18: =K17+L16 -> 0
B19: Debt Service Coverage Ratio (DSCR) | C19: =IF(C14>0,C7/C14,"N/A") -> N/A | D19: =IF(D14>0,C7/D14,"N/A") -> N/A | E19: =IF(E14>0,C7/E14,"N/A") -> N/A | F19: =IF(F14>0,C7/F14,"N/A") -> N/A | G19: =IF(G14>0,C7/G14,"N/A") -> N/A | H19: =IF(H14>0,C7/H14,"N/A") -> N/A | I19: =IF(I14>0,C7/I14,"N/A") -> N/A | J19: =IF(J14>0,C7/J14,"N/A") -> N/A | K19: =IF(K14>0,C7/K14,"N/A") -> N/A | L19: =IF(L14>0,C7/L14,"N/A") -> N/A
B20: DSCR ≥ 1.3x (lender threshold)? | C20: =IF(ISNUMBER(C18),IF(C18>=1.3,"YES","BELOW 1.3x"),"N/A") -> N/A | D20: =IF(ISNUMBER(D18),IF(D18>=1.3,"YES","BELOW 1.3x"),"N/A") -> BELOW 1.3x | E20: =IF(ISNUMBER(E18),IF(E18>=1.3,"YES","BELOW 1.3x"),"N/A") -> BELOW 1.3x | F20: =IF(ISNUMBER(F18),IF(F18>=1.3,"YES","BELOW 1.3x"),"N/A") -> BELOW 1.3x | G20: =IF(ISNUMBER(G18),IF(G18>=1.3,"YES","BELOW 1.3x"),"N/A") -> BELOW 1.3x | H20: =IF(ISNUMBER(H18),IF(H18>=1.3,"YES","BELOW 1.3x"),"N/A") -> BELOW 1.3x | I20: =IF(ISNUMBER(I18),IF(I18>=1.3,"YES","BELOW 1.3x"),"N/A") -> BELOW 1.3x | J20: =IF(ISNUMBER(J18),IF(J18>=1.3,"YES","BELOW 1.3x"),"N/A") -> BELOW 1.3x | ... L20: =IF(ISNUMBER(L18),IF(L18>=1.3,"YES","BELOW 1.3x"),"N/A") -> BELOW 1.3x

Sheet 10 - Sensitivities
B1: Tab 10 — Sensitivity Analysis
B2: Show impact of key risk variables on collected revenue and DSCR. State base assumption and downside/upside cases.
B3: Sensitivity Variable | C3: Base Case Assumption | D3: Downside Case | E3: Upside Case | F3: Bidder Comment
B4: Customer demand (total kWh sold) | C4: Base forecast from Tab 7 | D4: -20% of base | E4: +20% of base | F4: State main demand risk driver
B5: Revenue collection rate | C5: 90% of gross revenue billed | D5: 75% | E5: 95% | F5: Explain collection strategy and mitigation
B6: USD:NGN exchange rate | C6: Rate stated on Tab 1 | D6: +25% NGN depreciation | E6: -10% NGN appreciation | F6: State FX risk exposure and hedging approach
B7: Total CAPEX overrun | C7: 0% contingency | D7: +15% on total eligible CAPEX | E7: -5% on total eligible CAPEX | F7: State procurement strategy and fixed-price arrangements
B8: Tariff approval delay | C8: No delay | D8: 6-month delay to NERC approval | E8: Approval before commissioning | F8: State NERC engagement status and timeline
B9: Grid supply hours from DisCo | C9: Base case stated in Tab 6 | D9: -30% of base grid supply hours | E9: +20% of base grid supply hours | F9: Describe grid reliability risk and DER sizing buffer
B10: Battery replacement cost | C10: Base case stated in Tab 8 | D10: +20% on replacement cost | E10: -10% on replacement cost | F10: State warranty terms and replacement year assumption
A12: SENSITIVITY IMPACT ON KEY METRICS — BIDDER TO COMPLETE
B13: Sensitivity | C13: Downside DSCR (Year 5) | D13: Base DSCR (Year 5) | E13: Upside DSCR (Year 5) | F13: Comment
B14: Customer demand (total kWh sold)
B15: Revenue collection rate
B16: USD:NGN exchange rate
B17: Total CAPEX overrun
B18: Tariff approval delay
B19: Grid supply hours from DisCo
B20: Battery replacement cost

Sheet 11 - Milestone Schedule
B1: Tab 11 — Grant Disbursement Milestone Schedule
B2: Tranche percentages must match the grant agreement as confirmed in the Bid Data Sheet. Evidence column shows IVA requirements.
B3: Milestone | C3: Tranche % of Total Grant | D3: Grant Amount (USD) | E3: Evidence Required for Verification | F3: Expected Date
B4: Commissioning — DER system energised and NEMSA certified | C4: 40% (confirm in Bid Data Sheet) | D4: ='4 - Grant Request'!C6*0.4 -> 0 | E4: NEMSA commissioning certificate; as-built drawings; equipment serial list; commissioning test report; geotagged site inspection photos; IVA verification report
B5: Verified Connections — agreed customer count metered, onboarded, and receiving supply | C5: 40% (confirm in Bid Data Sheet) | D5: ='4 - Grant Request'!C6*0.4 -> 0 | E5: Customer register with meter IDs and GPS coordinates; customer category breakdown; activation records; IVA sample verification report; connection compliance certificate
B6: One-Year Utilisation/Performance — 12 months continuous operation meeting capacity utilisation, supply hours, and service quality thresholds | C6: 20% (confirm in Bid Data Sheet) | D6: ='4 - Grant Request'!C6*0.2 -> 0 | E6: 12-month metering report; capacity utilisation calculation; supply hours log; energy sold and collection rate data; SAIDI/SAIFI report; DisCo settlement records for 12 months; E&S compliance confirmation; IVA verification report
B7: TOTAL | D7: =SUM(D4:D6) -> 0
